LICENSE.txt
MANIFEST.in
README.rst
setup.py
blink1py/__init__.py
blink1py/blink1.py
blink1py/blink1_raw.py
blink1py.egg-info/PKG-INFO
blink1py.egg-info/SOURCES.txt
blink1py.egg-info/dependency_links.txt
blink1py.egg-info/top_level.txt