Metadata-Version: 1.0
Name: blink1py
Version: 0.1.0
Summary: blink(1) library wrapper
Home-page: https://github.com/TronPaul/blink1py
Author: Mark McGuire
Author-email: mark.b.mcg@gmail.com
License: Apache2
Platform: UNKNOWN
